coeus_unity/__init__.py
coeus_unity/assertions.py
coeus_unity/commands.py
coeus_unity/transform.py
coeus_test_unity-0.1.16.dist-info/LICENSE
coeus_test_unity-0.1.16.dist-info/METADATA
coeus_test_unity-0.1.16.dist-info/WHEEL
coeus_test_unity-0.1.16.dist-info/top_level.txt
coeus_test_unity-0.1.16.dist-info/RECORD
