Metadata-Version: 2.1
Name: coeus-test-unity
Version: 0.1.16
Summary: Unity commands and responses for coeus-python-framework.
Home-page: https://github.com/AgeOfLearning/coeus-unity-python-framework
Author: Devon Klompmaker
Author-email: devon.klompmaker@aofl.com
License: BSD 3-Clause License
Keywords: coeus-test-unity
Platform: UNKNOWN
Classifier: Development Status :: 2 - Pre-Alpha
Classifier: Intended Audience :: Developers
Classifier: License :: OSI Approved :: MIT License
Classifier: Natural Language :: English
Classifier: Programming Language :: Python :: 2
Classifier: Programming Language :: Python :: 2.7
Classifier: Programming Language :: Python :: 3
Classifier: Programming Language :: Python :: 3.4
Classifier: Programming Language :: Python :: 3.5
Classifier: Programming Language :: Python :: 3.6
Classifier: Programming Language :: Python :: 3.7
Requires-Dist: coeus-test (>=0.1.8)
